ChangeLog.md
LICENSE
MANIFEST.in
README-CN.md
README.md
setup.py
alibabacloud_vpc20180317/__init__.py
alibabacloud_vpc20180317/client.py
alibabacloud_vpc20180317/models.py
alibabacloud_vpc20180317.egg-info/PKG-INFO
alibabacloud_vpc20180317.egg-info/SOURCES.txt
alibabacloud_vpc20180317.egg-info/dependency_links.txt
alibabacloud_vpc20180317.egg-info/requires.txt
alibabacloud_vpc20180317.egg-info/top_level.txt